odoo10_addon_hr_employee_firstname-10.0.2.0.0-nspkg.pth
odoo/addons/hr_employee_firstname/README.rst
odoo/addons/hr_employee_firstname/__init__.py
odoo/addons/hr_employee_firstname/__manifest__.py
odoo/addons/hr_employee_firstname/init_hook.py
odoo/addons/hr_employee_firstname/i18n/ar.po
odoo/addons/hr_employee_firstname/i18n/cs_CZ.po
odoo/addons/hr_employee_firstname/i18n/de.po
odoo/addons/hr_employee_firstname/i18n/es.po
odoo/addons/hr_employee_firstname/i18n/fi.po
odoo/addons/hr_employee_firstname/i18n/fr.po
odoo/addons/hr_employee_firstname/i18n/hr.po
odoo/addons/hr_employee_firstname/i18n/hr_HR.po
odoo/addons/hr_employee_firstname/i18n/hr_employee_firstname.pot
odoo/addons/hr_employee_firstname/i18n/it.po
odoo/addons/hr_employee_firstname/i18n/lt.po
odoo/addons/hr_employee_firstname/i18n/nl_NL.po
odoo/addons/hr_employee_firstname/i18n/pt_BR.po
odoo/addons/hr_employee_firstname/i18n/ro.po
odoo/addons/hr_employee_firstname/i18n/sl.po
odoo/addons/hr_employee_firstname/models/__init__.py
odoo/addons/hr_employee_firstname/models/hr_employee.py
odoo/addons/hr_employee_firstname/static/description/icon.png
odoo/addons/hr_employee_firstname/tests/__init__.py
odoo/addons/hr_employee_firstname/tests/test_hr_employee_firstname.py
odoo/addons/hr_employee_firstname/views/hr_view.xml
odoo10_addon_hr_employee_firstname-10.0.2.0.0.dist-info/METADATA
odoo10_addon_hr_employee_firstname-10.0.2.0.0.dist-info/WHEEL
odoo10_addon_hr_employee_firstname-10.0.2.0.0.dist-info/namespace_packages.txt
odoo10_addon_hr_employee_firstname-10.0.2.0.0.dist-info/top_level.txt
odoo10_addon_hr_employee_firstname-10.0.2.0.0.dist-info/RECORD
