Metadata-Version: 2.1
Name: odoo10-addon-hr-employee-firstname
Version: 10.0.2.0.0
Summary: Adds First Name to Employee
Home-page: https://github.com/OCA/hr/
Author: Savoir-faire Linux, Fekete Mihai (Forest and Biomass Services Romania), Onestein, Odoo Community Association (OCA)
Author-email: support@odoo-community.org
License: AGPL-3
Platform: UNKNOWN
Classifier: Programming Language :: Python
Classifier: Framework :: Odoo
Classifier: License :: OSI Approved :: GNU Affero General Public License v3
Requires-Python: ~=2.7
Requires-Dist: odoo10-addon-partner-firstname
Requires-Dist: odoo (<10.1dev,>=10.0)
